trankit/__init__.py
trankit/__main__.py
trankit/config.py
trankit/pipeline.py
trankit/tpipeline.py
trankit/iterators/__init__.py
trankit/iterators/lemmatizer_iterators.py
trankit/iterators/mwt_iterators.py
trankit/iterators/ner_iterators.py
trankit/iterators/tagger_iterators.py
trankit/iterators/tokenizer_iterators.py
trankit/layers/__init__.py
trankit/layers/crf_layer.py
trankit/layers/seq2seq.py
trankit/models/__init__.py
trankit/models/base_models.py
trankit/models/classifiers.py
trankit/models/lemma_model.py
trankit/models/mwt_model.py
trankit/utils/__init__.py
trankit/utils/base_utils.py
trankit/utils/chuliu_edmonds.py
trankit/utils/conll.py
trankit/utils/ner_utils.py
trankit/utils/posdep_utils.py
trankit/utils/tbinfo.py
trankit/utils/tokenizer_utils.py
trankit/utils/mwt_lemma_utils/__init__.py
trankit/utils/mwt_lemma_utils/mwt_utils.py
trankit/utils/mwt_lemma_utils/seq2seq_utils.py
trankit/utils/mwt_lemma_utils/seq2seq_vocabs.py
trankit/utils/scorers/__init__.py
trankit/utils/scorers/conll18_ud_eval.py
trankit/utils/scorers/ner_scorer.py
trankit-1.1.2.dist-info/LICENSE
trankit-1.1.2.dist-info/METADATA
trankit-1.1.2.dist-info/WHEEL
trankit-1.1.2.dist-info/top_level.txt
trankit-1.1.2.dist-info/RECORD
