Metadata-Version: 2.1
Name: trankit
Version: 1.1.2
Summary: Trankit: A Light-Weight Transformer-based Toolkit for Multilingual Natural Language Processing
Home-page: https://github.com/nlp-uoregon/trankit
Author: NLP Group at the University of Oregon
Author-email: thien@cs.uoregon.edu
License: Apache License 2.0
Platform: UNKNOWN
Classifier: Development Status :: 4 - Beta
Classifier: Intended Audience :: Developers
Classifier: Intended Audience :: Education
Classifier: Intended Audience :: Science/Research
Classifier: Intended Audience :: Information Technology
Classifier: Topic :: Scientific/Engineering
Classifier: Topic :: Scientific/Engineering :: Artificial Intelligence
Classifier: Topic :: Scientific/Engineering :: Information Analysis
Classifier: Topic :: Text Processing
Classifier: Topic :: Text Processing :: Linguistic
Classifier: Topic :: Software Development
Classifier: Topic :: Software Development :: Libraries
Classifier: Programming Language :: Python :: 3.6
Classifier: Programming Language :: Python :: 3.7
Classifier: Programming Language :: Python :: 3.8
Classifier: Programming Language :: Python :: 3.9
Classifier: Programming Language :: Python :: 3.10
Requires-Dist: adapters (>=0.1.1)
Requires-Dist: transformers
Requires-Dist: numpy
Requires-Dist: protobuf
Requires-Dist: requests
Requires-Dist: torch (<=2.0.1,>=1.6.0)
Requires-Dist: tqdm (>=4.27)
Requires-Dist: langid (==1.1.6)
Requires-Dist: filelock
Requires-Dist: tokenizers (>=0.7.0)
Requires-Dist: regex (!=2019.12.17)
Requires-Dist: packaging
Requires-Dist: sentencepiece
Requires-Dist: sacremoses
Requires-Dist: six
